{"last_node_id": 12, "last_link_id": 11, "nodes": [{"id": 5, "type": "ImageListToImageBatch", "pos": [1800, 180], "size": {"0": 210, "1": 26}, "flags": {}, "order": 7, "mode": 0, "inputs": [{"name": "images", "type": "IMAGE", "link": 4}], "outputs": [{"name": "IMAGE", "type": "IMAGE", "links": [5, 6, 10], "shape": 3, "slot_index": 0}], "properties": {"Node name for S&R": "ImageListToImageBatch", "ttNbgOverride": {"color": "#223", "bgcolor": "#335", "groupcolor": "#88A"}}, "color": "#223", "bgcolor": "#335"}, {"id": 6, "type": "SaveImageExtended", "pos": [1860, 360], "size": [300, 600], "flags": {}, "order": 9, "mode": 0, "inputs": [{"name": "images", "type": "IMAGE", "link": 5}, {"name": "positive_text_opt", "type": "STRING", "link": null, "widget": {"name": "positive_text_opt"}}, {"name": "negative_text_opt", "type": "STRING", "link": null, "widget": {"name": "negative_text_opt"}}], "properties": {"Node name for S&R": "SaveImageExtended", "ttNbgOverride": {"color": "#223", "bgcolor": "#335", "groupcolor": "#88A"}}, "widgets_values": ["GraymanShuffle", "resolution", "GraymanShuffle", "resolution", "underscore", "basic, prompt", "disabled", "", "enabled", 3, "last", "disabled", "enabled", "", ""], "color": "#223", "bgcolor": "#335"}, {"id": 7, "type": "VHS_VideoCombine", "pos": [2193, 196], "size": [300, 793.65625], "flags": {}, "order": 10, "mode": 0, "inputs": [{"name": "images", "type": "IMAGE", "link": 6}, {"name": "audio", "type": "VHS_AUDIO", "link": null}, {"name": "batch_manager", "type": "VHS_BatchManager", "link": null}], "outputs": [{"name": "Filenames", "type": "VHS_FILENAMES", "links": null, "shape": 3}], "properties": {"Node name for S&R": "VHS_VideoCombine", "ttNbgOverride": {"color": "#223", "bgcolor": "#335", "groupcolor": "#88A"}}, "widgets_values": {"frame_rate": 30, "loop_count": 0, "filename_prefix": "GraymanShuffle", "format": "video/h264-mp4", "pix_fmt": "yuv420p10le", "crf": 19, "save_metadata": true, "pingpong": false, "save_output": true, "videopreview": {"hidden": false, "paused": false, "params": {"filename": "GraymanShuffle_00001.mp4", "subfolder": "", "type": "output", "format": "video/h264-mp4"}}}, "color": "#223", "bgcolor": "#335"}, {"id": 1, "type": "VHS_LoadVideo", "pos": [420, 120], "size": [240, 660], "flags": {}, "order": 0, "mode": 0, "inputs": [{"name": "batch_manager", "type": "VHS_BatchManager", "link": null}], "outputs": [{"name": "IMAGE", "type": "IMAGE", "links": [], "shape": 3, "slot_index": 0}, {"name": "frame_count", "type": "INT", "links": null, "shape": 3}, {"name": "audio", "type": "VHS_AUDIO", "links": null, "shape": 3}], "properties": {"Node name for S&R": "VHS_LoadVideo", "ttNbgOverride": {"color": "#223", "bgcolor": "#335", "groupcolor": "#88A"}}, "widgets_values": {"video": "shuffle.mp4", "force_rate": 0, "force_size": "Disabled", "custom_width": 512, "custom_height": 512, "frame_load_cap": 30, "skip_first_frames": 30, "select_every_nth": 1, "choose video to upload": "image", "videopreview": {"hidden": false, "paused": false, "params": {"frame_load_cap": 30, "skip_first_frames": 30, "force_rate": 0, "filename": "shuffle.mp4", "type": "input", "format": "video/mp4", "select_every_nth": 1}}}, "color": "#223", "bgcolor": "#335"}, {"id": 2, "type": "ImpactImageBatchToImageList", "pos": [780, 180], "size": {"0": 210, "1": 26}, "flags": {}, "order": 2, "mode": 0, "inputs": [{"name": "image", "type": "IMAGE", "link": 11}], "outputs": [{"name": "IMAGE", "type": "IMAGE", "links": [2, 7], "shape": 6, "slot_index": 0}], "properties": {"Node name for S&R": "ImpactImageBatchToImageList", "ttNbgOverride": {"color": "#223", "bgcolor": "#335", "groupcolor": "#88A"}}, "color": "#223", "bgcolor": "#335"}, {"id": 8, "type": "PreviewImage", "pos": [1020, 540], "size": [240, 240], "flags": {}, "order": 4, "mode": 0, "inputs": [{"name": "images", "type": "IMAGE", "link": 7}], "properties": {"Node name for S&R": "PreviewImage", "ttNbgOverride": {"color": "#223", "bgcolor": "#335", "groupcolor": "#88A"}}, "color": "#223", "bgcolor": "#335"}, {"id": 9, "type": "PreviewImage", "pos": [1320, 540], "size": [240, 240], "flags": {}, "order": 6, "mode": 0, "inputs": [{"name": "images", "type": "IMAGE", "link": 8}], "properties": {"Node name for S&R": "PreviewImage", "ttNbgOverride": {"color": "#223", "bgcolor": "#335", "groupcolor": "#88A"}}, "color": "#223", "bgcolor": "#335"}, {"id": 3, "type": "DWPreprocessor", "pos": [1020, 180], "size": {"0": 315, "1": 198}, "flags": {}, "order": 3, "mode": 0, "inputs": [{"name": "image", "type": "IMAGE", "link": 2}], "outputs": [{"name": "IMAGE", "type": "IMAGE", "links": [3, 8], "shape": 3, "slot_index": 0}, {"name": "POSE_KEYPOINT", "type": "POSE_KEYPOINT", "links": null, "shape": 3}], "properties": {"Node name for S&R": "DWPreprocessor", "ttNbgOverride": {"color": "#223", "bgcolor": "#335", "groupcolor": "#88A"}}, "widgets_values": ["enable", "enable", "enable", 512, "yolox_l.onnx", "dw-ll_ucoco_384.onnx"], "color": "#223", "bgcolor": "#335"}, {"id": 10, "type": "PreviewImage", "pos": [1629.2573592337044, 513.8334129549065], "size": [240, 240], "flags": {}, "order": 8, "mode": 0, "inputs": [{"name": "images", "type": "IMAGE", "link": 9}], "properties": {"Node name for S&R": "PreviewImage", "ttNbgOverride": {"color": "#223", "bgcolor": "#335", "groupcolor": "#88A"}}, "color": "#223", "bgcolor": "#335"}, {"id": 4, "type": "Image Remove Background (Alpha)", "pos": [1380, 180], "size": {"0": 315, "1": 106}, "flags": {}, "order": 5, "mode": 0, "inputs": [{"name": "images", "type": "IMAGE", "link": 3}], "outputs": [{"name": "images", "type": "IMAGE", "links": [4, 9], "shape": 3, "slot_index": 0}], "properties": {"Node name for S&R": "Image Remove Background (Alpha)", "ttNbgOverride": {"color": "#223", "bgcolor": "#335", "groupcolor": "#88A"}}, "widgets_values": ["background", 0, 1], "color": "#223", "bgcolor": "#335"}, {"id": 11, "type": "PreviewImage", "pos": [2063.6305589175645, 71.58044211974709], "size": [240, 240], "flags": {}, "order": 11, "mode": 0, "inputs": [{"name": "images", "type": "IMAGE", "link": 10, "slot_index": 0}], "properties": {"Node name for S&R": "PreviewImage", "ttNbgOverride": {"color": "#223", "bgcolor": "#335", "groupcolor": "#88A"}}, "color": "#223", "bgcolor": "#335"}, {"id": 12, "type": "LoadImageListFromDir //Inspire", "pos": [360, 900], "size": {"0": 315, "1": 150}, "flags": {}, "order": 1, "mode": 0, "outputs": [{"name": "IMAGE", "type": "IMAGE", "links": [11], "shape": 6, "slot_index": 0}, {"name": "MASK", "type": "MASK", "links": null, "shape": 6}], "properties": {"Node name for S&R": "LoadImageListFromDir //Inspire", "ttNbgOverride": {"color": "#223", "bgcolor": "#335", "groupcolor": "#88A"}}, "widgets_values": ["", 0, 0, false], "color": "#223", "bgcolor": "#335"}], "links": [[2, 2, 0, 3, 0, "IMAGE"], [3, 3, 0, 4, 0, "IMAGE"], [4, 4, 0, 5, 0, "IMAGE"], [5, 5, 0, 6, 0, "IMAGE"], [6, 5, 0, 7, 0, "IMAGE"], [7, 2, 0, 8, 0, "IMAGE"], [8, 3, 0, 9, 0, "IMAGE"], [9, 4, 0, 10, 0, "IMAGE"], [10, 5, 0, 11, 0, "IMAGE"], [11, 12, 0, 2, 0, "IMAGE"]], "groups": [], "config": {}, "extra": {}, "version": 0.4}